quick_mock/__init__.py
quick_mock-0.0.5.dist-info/LICENSE
quick_mock-0.0.5.dist-info/METADATA
quick_mock-0.0.5.dist-info/WHEEL
quick_mock-0.0.5.dist-info/entry_points.txt
quick_mock-0.0.5.dist-info/top_level.txt
quick_mock-0.0.5.dist-info/RECORD
