Metadata-Version: 2.1
Name: quick-mock
Version: 0.0.5
Summary: quick mock server
Home-page: https://github.com/qiujiajin/quick-mock
Author: Hugh
Author-email: 609799548@qq.com
License: MIT Licence
Platform: UNKNOWN
Classifier: Programming Language :: Python
Classifier: License :: OSI Approved :: MIT License
Classifier: Operating System :: OS Independent
License-File: LICENSE
Requires-Dist: flask (==1.1.0)
